jupyter_server_xarray_leaflet/__init__.py
jupyter_server_xarray_leaflet/handler.py
jupyter_server_xarray_leaflet/server_extension.py
jupyter_server_xarray_leaflet-0.2.3.data/data/etc/jupyter/jupyter_notebook_config.d/jupyter_server_xarray_leaflet.json
jupyter_server_xarray_leaflet-0.2.3.data/data/etc/jupyter/jupyter_server_config.d/jupyter_server_xarray_leaflet.json
jupyter_server_xarray_leaflet-0.2.3.dist-info/METADATA
jupyter_server_xarray_leaflet-0.2.3.dist-info/WHEEL
jupyter_server_xarray_leaflet-0.2.3.dist-info/licenses/LICENSE
jupyter_server_xarray_leaflet-0.2.3.dist-info/RECORD
