Metadata-Version: 2.1
Name: jupyter_server_xarray_leaflet
Version: 0.2.3
Summary: A Jupyter Server extension for xarray-leaflet
Project-URL: Homepage, https://github.com/xarray-contrib/xarray_leaflet/jupyter_server
Author-email: David Brochart <david.brochart@gmail.com>
License: MIT License
License-File: LICENSE
Keywords: jupyter,leaflet,server,xarray
Requires-Python: >=3.5
Requires-Dist: jupyter-server>=0.2.0
